{
  "Paper_Metadata": {
    "Paper_Title": "Additive manufacturing of an ultrastrong, deformable Al alloy with nanoscale intermetallics",
    "DOI": "10.1038/s41467-024-48693-4"
  },
  "items": [
    {
      "Sample_ID": "Al92Ti2Fe2Co2Ni2_LPBF",
      "Gradient_Material": false,
      "Gradient_Group_ID": null,
      "Composition_Info": {
        "Role": "Target",
        "Alloy_Name_Raw": "Al92Ti2Fe2Co2Ni2",
        "Nominal_Composition": {
          "Composition_Type": "at%",
          "Elements_Normalized": {
            "Al": 92.0,
            "Ti": 2.0,
            "Fe": 2.0,
            "Co": 2.0,
            "Ni": 2.0
          }
        },
        "Measured_Composition": {
          "Composition_Type": null,
          "Elements_Normalized": null,
          "Measurement_Method": null
        },
        "Note": "Nominal composition in at%; powder size -53+15 um gas atomized by Atlantic Equipment Engineering, Inc."
      },
      "Process_Info": {
        "Process_Category": "Laser Powder Bed Fusion (LPBF)",
        "Process_Text": {
          "original": "Gas atomized spherical powder (-53+15 um) fabricated by LPBF (SLM 125 HL) in Argon atmosphere (oxygen <1000 PPM) using 400 W IPG fiber laser (lambda=1070 nm); laser power 200-300 W, scan speed 1200 mm/s, hatch space 100 um, layer thickness 30 um, spot size 70 um; build plate preheated to 200 C, layer rotation 67 deg.",
          "simplified": "LPBF of Al92Ti2Fe2Co2Ni2 powder with laser power 200-300 W, scan speed 1200 mm/s, layer thickness 30 um, hatch spacing 100 um, in Ar atmosphere."
        },
        "Equipment": "SLM 125 HL metal 3D printer; IPG fiber laser 400 W",
        "Key_Params": {
          "Laser_Power_W": [
            200,
            250,
            300
          ],
          "Scanning_Speed_mm_s": 1200.0,
          "Layer_Thickness_um": 30.0,
          "Hatch_Spacing_um": 100.0,
          "Build_Plate_Temperature_K": 473.15,
          "Protective_Atmosphere": "Argon (<1000 PPM O2)",
          "Powder_Size_range_um": "-53+15",
          "Spot_Size_um": 70.0,
          "Layer_Rotation_deg": 67.0,
          "Volumetric_Energy_Density_J_mm3": null
        }
      },
      "Microstructure_Info": {
        "Microstructure_Text": {
          "original": "Heterogeneous microstructure with coarse rosettes in melt pool center (36 vol.%) and fine rosettes near boundaries (97 vol.%). Fine rosettes have Al3Ti cores with alternating Al3Ti and Al9(Fe,Co,Ni)2 lamellae (20-60 nm thick). Coarse rosettes have lamellae 150-300 nm thick. Cellular precipitates (4 vol.%) of Al9(Fe,Co,Ni)2 in coarse rosette regions. Al matrix: 60 vol.% in center, 3 vol.% near boundaries. High-density defects in Al3Ti; Al9(Fe,Co,Ni)2 relatively defect-free. Orientation relationship: [130]Al3Ti // [100]Al9(Fe,Co,Ni)2, (002)Al3Ti // (001)Al9(Fe,Co,Ni)2.",
          "simplified": "Heterogeneous rosette microstructure: fine rosettes (20-60 nm lamellae) near melt pool boundaries, coarse rosettes (150-300 nm lamellae) in melt pool center; Al9(Fe,Co,Ni)2 and Al3Ti intermetallics with Al matrix."
        },
        "Main_Phase": "FCC Al matrix",
        "Precipitates": [
          {
            "Phase_Type": "Al9(Fe,Co,Ni)2",
            "Volume_Fraction_pct": null
          },
          {
            "Phase_Type": "Al3Ti",
            "Volume_Fraction_pct": null
          }
        ],
        "Porosity_pct": null,
        "Relative_Density_pct": null,
        "Grain_Size_avg_um": 1.0,
        "Precipitate_Size_avg_nm": null,
        "Precipitate_Volume_Fraction_pct": null,
        "Phase_Fraction_pct": null,
        "Advanced_Quantitative_Features": {
          "Cellular_precipitate_vol_pct": 4.0,
          "Fine_rosette_vol_pct_near_MP_boundary": 97.0,
          "Coarse_rosette_vol_pct_in_MP_center": 36.0,
          "Al_matrix_vol_pct_near_MP_boundary": 3.0,
          "Al_matrix_vol_pct_in_MP_center": 60.0,
          "Fine_rosette_lamella_thickness_nm": "20-60",
          "Coarse_rosette_lamella_thickness_nm": "150-300",
          "Fine_rosette_lamella_thickness_avg_nm": 40.0,
          "Coarse_rosette_lamella_thickness_avg_nm": 225.0,
          "Melt_pool_width_um": 120.0,
          "Melt_pool_depth_um": 80.0,
          "Dislocation_density_m2": [
            47000000000000.0,
            100000000000000.0
          ],
          "Dislocation_strengthening_MPa": [
            25.0,
            36.0
          ]
        }
      },
      "Properties_Info": [
        {
          "Property_Name": "Ultimate_Strength_Compressive",
          "Test_Condition": "Bulk compression tests; strain rate 1e-3 s-1",
          "Value_Numeric": 800.0,
          "Value_Range": null,
          "Value_StdDev": null,
          "Unit": "MPa",
          "Test_Temperature_K": 298.15,
          "Strain_Rate_s1": "1e-3",
          "Tensile_Speed_mm_min": null,
          "Hardness_Load": null,
          "Hardness_Dwell_Time_s": null,
          "Data_Source": "text",
          "Test_Specimen": "Cylindrical specimens: 6x12 mm",
          "Note": "200 W laser power; ultra-high engineering stress exceeding 800 MPa"
        },
        {
          "Property_Name": "Elastic_Modulus",
          "Test_Condition": "Berkovich tip nanoindentation, 800 nm depth",
          "Value_Numeric": 140.0,
          "Value_Range": "130-150",
          "Value_StdDev": null,
          "Unit": "GPa",
          "Test_Temperature_K": 298.15,
          "Strain_Rate_s1": null,
          "Tensile_Speed_mm_min": null,
          "Hardness_Load": null,
          "Hardness_Dwell_Time_s": null,
          "Data_Source": "text",
          "Test_Specimen": "10x10x5 mm cubic samples",
          "Note": "Fine rosette regions: 140-150 GPa; coarse rosette regions: 130-140 GPa"
        },
        {
          "Property_Name": "Back_Stress",
          "Test_Condition": "Multiple loading-unloading micropillar compression; fine rosette region",
          "Value_Numeric": 600.0,
          "Value_Range": null,
          "Value_StdDev": null,
          "Unit": "MPa",
          "Test_Temperature_K": 298.15,
          "Strain_Rate_s1": "5e-3",
          "Tensile_Speed_mm_min": null,
          "Hardness_Load": null,
          "Hardness_Dwell_Time_s": null,
          "Data_Source": "text",
          "Test_Specimen": null,
          "Note": "Prominent back stress ~600 MPa in fine rosette regions with higher flow strength"
        },
        {
          "Property_Name": "Back_Stress",
          "Test_Condition": "Multiple loading-unloading micropillar compression; coarse rosette region",
          "Value_Numeric": 250.0,
          "Value_Range": null,
          "Value_StdDev": null,
          "Unit": "MPa",
          "Test_Temperature_K": 298.15,
          "Strain_Rate_s1": "5e-3",
          "Tensile_Speed_mm_min": null,
          "Hardness_Load": null,
          "Hardness_Dwell_Time_s": null,
          "Data_Source": "text",
          "Test_Specimen": null,
          "Note": "Back stress ~250 MPa in coarse rosette regions"
        },
        {
          "Property_Name": "Compressive_Strain_Total",
          "Test_Condition": "Bulk compression; strain rate 1e-3 s-1",
          "Value_Numeric": 20.0,
          "Value_Range": null,
          "Value_StdDev": null,
          "Unit": "%",
          "Test_Temperature_K": 298.15,
          "Strain_Rate_s1": "1e-3",
          "Tensile_Speed_mm_min": null,
          "Hardness_Load": null,
          "Hardness_Dwell_Time_s": null,
          "Data_Source": "text",
          "Test_Specimen": "Cylindrical specimens: 6x12 mm",
          "Note": "200 W laser power; substantial plastic deformability ~20% with barreling phenomenon"
        },
        {
          "Property_Name": "Compressive_Strain_Total",
          "Test_Condition": "Bulk compression; 250-300 W laser power; strain rate 1e-3 s-1",
          "Value_Numeric": 12.5,
          "Value_Range": "5-20",
          "Value_StdDev": null,
          "Unit": "%",
          "Test_Temperature_K": 298.15,
          "Strain_Rate_s1": "1e-3",
          "Tensile_Speed_mm_min": null,
          "Hardness_Load": null,
          "Hardness_Dwell_Time_s": null,
          "Data_Source": "text",
          "Test_Specimen": "Cylindrical specimens: 6x12 mm",
          "Note": "250-300 W laser power; 5-20% compressive strain"
        },
        {
          "Property_Name": "Compressive_Yield_Strength",
          "Test_Condition": "Bulk compression tests on MTS framework with 30 kN load cell; strain rate 1e-3 s-1; cylindrical specimens 6x12 mm",
          "Value_Numeric": 800.0,
          "Value_Range": null,
          "Value_StdDev": null,
          "Unit": "MPa",
          "Test_Temperature_K": 298.15,
          "Strain_Rate_s1": "1e-3",
          "Tensile_Speed_mm_min": null,
          "Hardness_Load": null,
          "Hardness_Dwell_Time_s": null,
          "Data_Source": "text",
          "Test_Specimen": "Cylindrical specimens: height 12 mm, diameter 6 mm",
          "Note": "200 W laser power; engineering stress exceeding 800 MPa with ~20% plastic strain"
        },
        {
          "Property_Name": "Compressive_Yield_Strength",
          "Test_Condition": "Bulk compression tests; 250-300 W laser power; strain rate 1e-3 s-1",
          "Value_Numeric": 550.0,
          "Value_Range": null,
          "Value_StdDev": null,
          "Unit": "MPa",
          "Test_Temperature_K": 298.15,
          "Strain_Rate_s1": "1e-3",
          "Tensile_Speed_mm_min": null,
          "Hardness_Load": null,
          "Hardness_Dwell_Time_s": null,
          "Data_Source": "text",
          "Test_Specimen": "Cylindrical specimens: 6x12 mm",
          "Note": "250 W and 300 W laser power; flow stress decreases to 550 MPa with 5-20% compressive strain"
        },
        {
          "Property_Name": "Micropillar_Compressive_Flow_Stress",
          "Test_Condition": "In situ SEM micropillar compression; 300 W laser; fine rosette region; strain rate 5e-3 s-1; micropillar: height 10 um, diameter 5 um, aspect ratio 2:1",
          "Value_Numeric": 950.0,
          "Value_Range": "900-1000",
          "Value_StdDev": null,
          "Unit": "MPa",
          "Test_Temperature_K": 298.15,
          "Strain_Rate_s1": "5e-3",
          "Tensile_Speed_mm_min": null,
          "Hardness_Load": null,
          "Hardness_Dwell_Time_s": null,
          "Data_Source": "text",
          "Test_Specimen": "FIB-fabricated micropillars: height 10 um, diameter 5 um; 10 and 20 um diamond flat-punch tips",
          "Note": "Fine rosette regions can exceed 900 MPa; true flow stress reaching 1 GPa; engineering stress 1.18 GPa; at least 15% plasticity"
        },
        {
          "Property_Name": "Micropillar_Compressive_Flow_Stress",
          "Test_Condition": "In situ SEM micropillar compression; 300 W laser; coarse rosette region; strain rate 5e-3 s-1",
          "Value_Numeric": 500.0,
          "Value_Range": null,
          "Value_StdDev": null,
          "Unit": "MPa",
          "Test_Temperature_K": 298.15,
          "Strain_Rate_s1": "5e-3",
          "Tensile_Speed_mm_min": null,
          "Hardness_Load": null,
          "Hardness_Dwell_Time_s": null,
          "Data_Source": "text",
          "Test_Specimen": "FIB-fabricated micropillars: height 10 um, diameter 5 um",
          "Note": "Coarse rosette region flow stress ~500 MPa"
        },
        {
          "Property_Name": "Nanoindentation_Hardness",
          "Test_Condition": "Berkovich tip, displacement-control mode, 800 nm depth, 100x100 um area with 121 indents (10 um spacing)",
          "Value_Numeric": 3.5,
          "Value_Range": "2.5-4.5",
          "Value_StdDev": null,
          "Unit": "GPa",
          "Test_Temperature_K": 298.15,
          "Strain_Rate_s1": null,
          "Tensile_Speed_mm_min": null,
          "Hardness_Load": null,
          "Hardness_Dwell_Time_s": null,
          "Data_Source": "text",
          "Test_Specimen": "10x10x5 mm cubic samples",
          "Note": "Fine rosette regions near melt pool boundaries: 3.5-4.5 GPa; coarse rosette regions in melt pool center: 2.5-3.0 GPa"
        },
        {
          "Property_Name": "Uniform_Deformation_Strain",
          "Test_Condition": "Considere criterion analysis on true stress-strain curves",
          "Value_Numeric": 7.0,
          "Value_Range": null,
          "Value_StdDev": null,
          "Unit": "%",
          "Test_Temperature_K": 298.15,
          "Strain_Rate_s1": null,
          "Tensile_Speed_mm_min": null,
          "Hardness_Load": null,
          "Hardness_Dwell_Time_s": null,
          "Data_Source": "image",
          "Test_Specimen": null,
          "Note": "Uniform deformation strain at 7% followed by long toughing stages"
        }
      ]
    }
  ]
}